MANIFEST.in
README.md
setup.py
garrison/__init__.py
garrison/client.py
garrison/garrison.proto
garrison/garrison_pb2.py
garrison/garrison_pb2_grpc.py
garrison/server.py
garrison/backends/__init__.py
garrison/backends/rocksdb.py
garrison_server.egg-info/PKG-INFO
garrison_server.egg-info/SOURCES.txt
garrison_server.egg-info/dependency_links.txt
garrison_server.egg-info/requires.txt
garrison_server.egg-info/top_level.txt
garrison_server.egg-info/zip-safe
images/logo.png
tests/__init__.py
tests/test_backends.py
tests/test_server.py