Metadata-Version: 2.1
Name: garrison-server
Version: 0.1.0
Summary: Queue server base on RocksDB as a KV-Store backend and gRPC as an interface
Home-page: https://github.com/intsights/garrison
Author: Gal Ben David
Author-email: gal@intsights.com
License: MIT
Project-URL: Source, https://github.com/intsights/garrison
Keywords: rocksdb db database queue fastapi
Platform: UNKNOWN
Classifier: License :: OSI Approved :: MIT License
Classifier: Programming Language :: Python :: 3.6
Classifier: Programming Language :: Python :: 3.7
Classifier: Programming Language :: Python :: 3.8
Requires-Python: >=3.6
